byarse/__init__.py
byarse-1.2.0.dist-info/LICENSE
byarse-1.2.0.dist-info/METADATA
byarse-1.2.0.dist-info/WHEEL
byarse-1.2.0.dist-info/top_level.txt
byarse-1.2.0.dist-info/RECORD
