Metadata-Version: 2.1
Name: byarse
Version: 1.2.0
Summary: Serialize Arguments as Bytes!
Home-page: https://github.com/netriza/byarse
Author: Netriza
Author-email: info@netriza.ml
License: UNKNOWN
Platform: UNKNOWN
Classifier: Programming Language :: Python :: 3
Classifier: License :: OSI Approved :: MIT License
Classifier: Operating System :: OS Independent
Requires-Python: >=3
